shift_left_secure/__init__.py
shift_left_secure/__main__.py
shift_left_secure/chatgpt_api.py
shift_left_secure/gh_action.py
shift_left_secure/git_handler.py
shift_left_secure/utils.py
shift_left_secure-0.2.3.dist-info/METADATA
shift_left_secure-0.2.3.dist-info/WHEEL
shift_left_secure-0.2.3.dist-info/RECORD
