Metadata-Version: 2.1
Name: shift-left-secure
Version: 0.2.3
Summary: Mitigate vulnerabilities before pushing code to github/gitlab/bitbucket
Author: Dhrumil Mistry
Author-email: 56185972+dmdhrumilmistry@users.noreply.github.com
Requires-Python: >=3.8,<4.0
Classifier: Programming Language :: Python :: 3
Classifier: Programming Language :: Python :: 3.8
Classifier: Programming Language :: Python :: 3.9
Classifier: Programming Language :: Python :: 3.10
Classifier: Programming Language :: Python :: 3.11
Requires-Dist: gitpython (==3.1.18)
Requires-Dist: openai (>=0.27.5,<0.28.0)
Requires-Dist: pygithub (>=1.58.1,<2.0.0)
Requires-Dist: python-dotenv (>=1.0.0,<2.0.0)
